pickly/__init__.py
pickly/pickly.py
pickly-1.0.dist-info/DESCRIPTION.rst
pickly-1.0.dist-info/METADATA
pickly-1.0.dist-info/RECORD
pickly-1.0.dist-info/WHEEL
pickly-1.0.dist-info/metadata.json
pickly-1.0.dist-info/top_level.txt
