Metadata-Version: 2.0
Name: pickly
Version: 1.0
Summary: JSON object mapping in Python
Home-page: http://github.com/itsnauman/pickly
Author: Nauman Ahmad
Author-email: nauman-ahmad@outlook.com
License: MIT
Platform: UNKNOWN
